ypostgres_lib/__init__.py
ypostgres_lib/postgres_lib.py
ypostgres_lib/vector_embeddings.py
ypostgres_lib-3.0.0.dist-info/LICENSE
ypostgres_lib-3.0.0.dist-info/METADATA
ypostgres_lib-3.0.0.dist-info/WHEEL
ypostgres_lib-3.0.0.dist-info/top_level.txt
ypostgres_lib-3.0.0.dist-info/RECORD
